{
  "triggered_at": "2026-03-26T16:04:52Z",
  "changed": [
    {
      "repo": "HansKristian-Work/vkd3d-proton",
      "name": "VKD3D-Proton",
      "old": "c3bc3dc",
      "new": "cc9d6cc",
      "full": "cc9d6cc7c765dfeaed2981f77ab8e75ba662629c",
      "msg": "vkd3d: Add missing barrier in Spider Man 2.",
      "date": "2026-03-26T15:51:26Z"
    },
    {
      "repo": "mesa/mesa",
      "name": "Mesa (Turnip)",
      "old": "0d8e235",
      "new": "06e5026",
      "full": "06e5026e28e38f46bf3b1c32a61fecf943b1f51e",
      "msg": "docs: add GL_NV_timeline_semaphore support for radeonsi",
      "date": "2026-03-26T14:26:56.000+00:00"
    }
  ]
}
